MANIFEST.in
README.md
requirements.txt
setup.cfg
setup.py
extraction/__init__.py
extraction/model.py
extraction/utils.py
extraction/algorithms/__init__.py
extraction/algorithms/nmf.py
test/test_model.py
test/test_nmf.py
thunder_extraction.egg-info/PKG-INFO
thunder_extraction.egg-info/SOURCES.txt
thunder_extraction.egg-info/dependency_links.txt
thunder_extraction.egg-info/requires.txt
thunder_extraction.egg-info/top_level.txt