Metadata-Version: 1.0
Name: thunder-extraction
Version: 1.1.0
Summary: algorithms for feature extraction from spatio-temporal data
Home-page: https://github.com/thunder-project/thunder-extraction
Author: freeman-lab
Author-email: the.freeman.lab@gmail.com
License: MIT
Platform: UNKNOWN
